adestis_netbox_plugin_account_management/__init__.py
adestis_netbox_plugin_account_management/navigation.py
adestis_netbox_plugin_account_management/urls.py
adestis_netbox_plugin_account_management/version.py
adestis_netbox_plugin_account_management/api/__init__.py
adestis_netbox_plugin_account_management/api/nested_serializer.py
adestis_netbox_plugin_account_management/api/urls.py
adestis_netbox_plugin_account_management/api/views.py
adestis_netbox_plugin_account_management/api/serializers/__init__.py
adestis_netbox_plugin_account_management/api/serializers/login_credentials_serializer.py
adestis_netbox_plugin_account_management/api/serializers/ssh_key_serializer.py
adestis_netbox_plugin_account_management/api/serializers/system_serializer.py
adestis_netbox_plugin_account_management/filtersets/__init__.py
adestis_netbox_plugin_account_management/filtersets/login_credentials.py
adestis_netbox_plugin_account_management/filtersets/ssh_key.py
adestis_netbox_plugin_account_management/filtersets/system.py
adestis_netbox_plugin_account_management/forms/__init__.py
adestis_netbox_plugin_account_management/forms/login_credentials.py
adestis_netbox_plugin_account_management/forms/ssh_key.py
adestis_netbox_plugin_account_management/forms/system.py
adestis_netbox_plugin_account_management/migrations/0001_initial.py
adestis_netbox_plugin_account_management/migrations/0002_alter_system_system_url.py
adestis_netbox_plugin_account_management/migrations/0003_remove_logincredentials_adestis_netbox_plugin_account_management_logincredentials_unique_login_crede.py
adestis_netbox_plugin_account_management/migrations/0004_alter_logincredentials_options_alter_person_options_and_more.py
adestis_netbox_plugin_account_management/migrations/0005_person_mitigation.py
adestis_netbox_plugin_account_management/migrations/0006_fix_constraint_logincredentials.py
adestis_netbox_plugin_account_management/migrations/0007_remove_logincredentials_person.py
adestis_netbox_plugin_account_management-1.9.6.dist-info/licenses/LICENSE
adestis_netbox_plugin_account_management-1.9.6.dist-info/METADATA
adestis_netbox_plugin_account_management-1.9.6.dist-info/WHEEL
adestis_netbox_plugin_account_management-1.9.6.dist-info/top_level.txt
adestis_netbox_plugin_account_management-1.9.6.dist-info/RECORD
